region_grow/__init__.py
region_grow/classifiers.py
region_grow/functions.py
region_grow/region.py
region_grow/region_grow.py
region_grow-1.0.4.dist-info/LICENSE
region_grow-1.0.4.dist-info/METADATA
region_grow-1.0.4.dist-info/WHEEL
region_grow-1.0.4.dist-info/top_level.txt
region_grow-1.0.4.dist-info/RECORD
