Metadata-Version: 2.1
Name: region-grow
Version: 1.0.4
Summary: Creates a new polygon locally given a set of points using a region grow algorithm approach and a satellite image in GeoTIFF format. The polygon output format is ESRI Shapefile
Home-page: https://github.com/ggonzr/region_grow
Author: Geovanny Andres Gonzalez
Author-email: ga.gonzalezr@uniandes.edu.co
License: MIT
Keywords: raster region grow
Platform: UNKNOWN
Classifier: Intended Audience :: Developers
Classifier: Intended Audience :: Information Technology
Classifier: Intended Audience :: Science/Research
Classifier: License :: OSI Approved :: MIT License
Classifier: Programming Language :: Python :: 3.7
Classifier: Programming Language :: Python :: 3
Classifier: Topic :: Scientific/Engineering :: GIS
Requires-Python: >=3.7
Requires-Dist: Shapely
Requires-Dist: numpy
Requires-Dist: pandas
Requires-Dist: scipy
Requires-Dist: rasterio
Requires-Dist: geopandas
